inputless_analytics/__init__.py
inputless_analytics/aggregators/__init__.py
inputless_analytics/aggregators/anomaly_aggregator.py
inputless_analytics/aggregators/pattern_aggregator.py
inputless_analytics/aggregators/trend_aggregator.py
inputless_analytics/analytics_engine.py
inputless_analytics/analyzers/__init__.py
inputless_analytics/analyzers/behavior_analyzer.py
inputless_analytics/analyzers/conversion_analyzer.py
inputless_analytics/analyzers/engagement_analyzer.py
inputless_analytics/analyzers/retention_analyzer.py
inputless_analytics/correlation_finder.py
inputless_analytics/insights_generator.py
inputless_analytics/models/__init__.py
inputless_analytics/models/analytics_result.py
inputless_analytics/models/insight.py
inputless_analytics/models/recommendation.py
inputless_analytics/predictors/__init__.py
inputless_analytics/predictors/behavior_predictor.py
inputless_analytics/predictors/outcome_predictor.py
inputless_analytics/recommendations.py
inputless_analytics/trend_analyzer.py
inputless_analytics/utils/__init__.py
inputless_analytics/utils/scoring.py
inputless_analytics-1.0.2.dist-info/METADATA
inputless_analytics-1.0.2.dist-info/WHEEL
inputless_analytics-1.0.2.dist-info/entry_points.txt
inputless_analytics-1.0.2.dist-info/RECORD
