Metadata-Version: 2.4
Name: inputless-analytics
Version: 1.0.2
Summary: Analytics engine, insights generation, and recommendation system
Author: Inputless Team
Author-email: team@inputless.io
Requires-Python: >=3.11,<3.14
Classifier: Programming Language :: Python :: 3
Classifier: Programming Language :: Python :: 3.11
Classifier: Programming Language :: Python :: 3.12
Classifier: Programming Language :: Python :: 3.13
Provides-Extra: statsforecast
Requires-Dist: numpy (>=1.26.3,<2.0.0)
Requires-Dist: pandas (>=2.2.0,<3.0.0)
Requires-Dist: pydantic (>=2.5.3,<3.0.0)
Requires-Dist: scikit-learn (>=1.4.0,<2.0.0)
Requires-Dist: scipy (>=1.11.4,<2.0.0)
Requires-Dist: statsforecast (>=2.0.0,<3.0.0) ; extra == "statsforecast"
Requires-Dist: statsmodels (>=0.14.1,<0.15.0)
